gh_star_count/__main__.py
gh_star_count/cli/__init__.py
gh_star_count/cli/count_stars.py
gh_star_count/cli/count_stars_scrapping.py
gh_star_count/cli/desc_update.py
gh_star_count/cli/status_update.py
gh_star_count/cli/test_count_stars.py
gh_star_count/cli/test_count_stars_scrapping.py
gh_star_count/cli/test_desc_update.py
gh_star_count/cli/test_status_update.py
gh_star_count-1.1.0.dist-info/LICENSE
gh_star_count-1.1.0.dist-info/WHEEL
gh_star_count-1.1.0.dist-info/METADATA
gh_star_count-1.1.0.dist-info/RECORD
